ivt/__init__.py
ivt/config.py
ivt/connector.py
ivt/io.py
ivt/loss.py
ivt/model.py
ivt/parameter.py
ivt/renderer.py
ivt/sampling.py
ivt/scene.py
ivt/transform.py
ivt/connectors/__init__.py
ivt/connectors/psdr_jit_connector.py
ivt-0.1.5.dist-info/LICENSE
ivt-0.1.5.dist-info/WHEEL
ivt-0.1.5.dist-info/METADATA
ivt-0.1.5.dist-info/RECORD
