Metadata-Version: 2.1
Name: ivt
Version: 0.1.5
Summary: Inverse-Rendering Toolkit
Author-email: Guangyan Cai <gcai3@uci.edu>
Requires-Python: >=3.8
Requires-Dist: imageio >= 2.27.0
Requires-Dist: imageio-freeimage
Requires-Dist: numpy
Requires-Dist: gin-config
Requires-Dist: gpytoolbox
Project-URL: Home, https://github.com/uci-rendering/inv-render-toolkit
